MANIFEST.in
README.md
setup.cfg
setup.py
ansi2utf8/__init__.py
ansi2utf8/main.py