Metadata-Version: 1.0
Name: ansi2utf8
Version: 0.2.0
Summary: ANSI to UTF-8
Home-page: https://github.com/SmilingXinyi/ansi2utf8
Author: blaite
Author-email: smilingxinyi@gmail.com
License: MIT
Keywords: a2u ansi2utf8
Platform: UNKNOWN
